blastplus/__init__.py
blastplus/forms.py
blastplus/settings.py
blastplus/test_settings.py
blastplus/urls.py
blastplus/utils.py
blastplus/views.py
blastplus/__pycache__/__init__.cpython-36.pyc
blastplus/__pycache__/__init__.cpython-37.pyc
blastplus/__pycache__/forms.cpython-36.pyc
blastplus/__pycache__/forms.cpython-37.pyc
blastplus/__pycache__/settings.cpython-36.pyc
blastplus/__pycache__/settings.cpython-37.pyc
blastplus/__pycache__/test_settings.cpython-36.pyc
blastplus/__pycache__/test_settings.cpython-37.pyc
blastplus/__pycache__/urls.cpython-36.pyc
blastplus/__pycache__/urls.cpython-37.pyc
blastplus/__pycache__/utils.cpython-36.pyc
blastplus/__pycache__/utils.cpython-37.pyc
blastplus/__pycache__/views.cpython-36.pyc
blastplus/__pycache__/views.cpython-37.pyc
blastplus/features/__init__.py
blastplus/features/record.py
blastplus/features/__pycache__/__init__.cpython-36.pyc
blastplus/features/__pycache__/__init__.cpython-37.pyc
blastplus/features/__pycache__/record.cpython-36.pyc
blastplus/features/__pycache__/record.cpython-37.pyc
blastplus/sampledata/blast.xml
blastplus/sampledata/sample_nucl.fasta
blastplus/sampledata/sample_prot.fasta
blastplus/sampledata/sample_db1/sample_db.fasta
blastplus/sampledata/sample_db1/sample_db.nhd
blastplus/sampledata/sample_db1/sample_db.nhi
blastplus/sampledata/sample_db1/sample_db.nhr
blastplus/sampledata/sample_db1/sample_db.nin
blastplus/sampledata/sample_db1/sample_db.nnd
blastplus/sampledata/sample_db1/sample_db.nni
blastplus/sampledata/sample_db1/sample_db.nog
blastplus/sampledata/sample_db1/sample_db.nsd
blastplus/sampledata/sample_db1/sample_db.nsi
blastplus/sampledata/sample_db1/sample_db.nsq
blastplus/sampledata/sample_db2/sample_db2.fasta
blastplus/sampledata/sample_db2/sample_db2.nhd
blastplus/sampledata/sample_db2/sample_db2.nhi
blastplus/sampledata/sample_db2/sample_db2.nhr
blastplus/sampledata/sample_db2/sample_db2.nin
blastplus/sampledata/sample_db2/sample_db2.nnd
blastplus/sampledata/sample_db2/sample_db2.nni
django_blastplus-3.0.0.dist-info/AUTHORS
django_blastplus-3.0.0.dist-info/LICENSE
django_blastplus-3.0.0.dist-info/METADATA
django_blastplus-3.0.0.dist-info/WHEEL
django_blastplus-3.0.0.dist-info/top_level.txt
django_blastplus-3.0.0.dist-info/RECORD
