Metadata-Version: 2.1
Name: django-blastplus
Version: 3.0.0
Summary: A simple Django app to conduct web-based blast+ local alignment search.
Home-page: https://github.com/michal-stuglik/django-blastplus
Author: Michal Stuglik
Author-email: stuglik@gmail.com
License: MIT License
Platform: UNKNOWN
Classifier: Environment :: Web Environment
Classifier: Framework :: Django :: 3.0
Classifier: Intended Audience :: Developers
Classifier: Intended Audience :: Science/Research
Classifier: License :: OSI Approved :: MIT License
Classifier: Operating System :: OS Independent
Classifier: Programming Language :: Python :: 3.6
Classifier: Programming Language :: Python :: 3.7
Classifier: Topic :: Internet :: WWW/HTTP
Classifier: Topic :: Scientific/Engineering :: Bio-Informatics
